README.md
setup.py
tartiflette_plugin_time_it/__init__.py
tartiflette_plugin_time_it.egg-info/PKG-INFO
tartiflette_plugin_time_it.egg-info/SOURCES.txt
tartiflette_plugin_time_it.egg-info/dependency_links.txt
tartiflette_plugin_time_it.egg-info/requires.txt
tartiflette_plugin_time_it.egg-info/top_level.txt