Metadata-Version: 2.1
Name: tartiflette-plugin-time-it
Version: 1.0.0
Summary: A tartiflette plugin that will print execution duration of a field
Home-page: https://github.com/tartiflette/tartiflette-plugin-time-it
Author: Aurelien Busi
Author-email: aurelien.busi@dailymotion.com
License: MIT
Keywords: graphql protocol api tartiflette timeit
Platform: UNKNOWN
Classifier: Intended Audience :: Developers
Classifier: Topic :: Software Development :: Libraries
Classifier: Programming Language :: Python :: 3.6
Classifier: Programming Language :: Python :: Implementation :: PyPy
Provides-Extra: test
